parallelworks_client/__init__.py
parallelworks_client/auth.py
parallelworks_client-6.12.0.dist-info/METADATA
parallelworks_client-6.12.0.dist-info/WHEEL
parallelworks_client-6.12.0.dist-info/RECORD
