Metadata-Version: 2.4
Name: parallelworks-client
Version: 6.12.0
Summary: Official Python SDK for Parallel Works ACTIVATE
Project-URL: Homepage, https://github.com/parallelworks/sdk
Project-URL: Documentation, https://parallelworks.com/docs
Project-URL: Repository, https://github.com/parallelworks/sdk
Project-URL: Issues, https://github.com/parallelworks/sdk/issues
Author-email: Parallel Works <support@parallelworks.com>
License-Expression: MIT
Keywords: activate,api,client,hpc,parallelworks,sdk
Classifier: Development Status :: 4 - Beta
Classifier: Intended Audience :: Developers
Classifier: License :: OSI Approved :: MIT License
Classifier: Programming Language :: Python :: 3
Classifier: Programming Language :: Python :: 3.9
Classifier: Programming Language :: Python :: 3.10
Classifier: Programming Language :: Python :: 3.11
Classifier: Programming Language :: Python :: 3.12
Classifier: Typing :: Typed
Requires-Python: >=3.9
Requires-Dist: attrs>=21.3.0
Requires-Dist: httpx>=0.27.0
Requires-Dist: pydantic>=2.0.0
Requires-Dist: python-dateutil>=2.8.0
